hhaven/__init__.py
hhaven/client.py
hhaven/decorators.py
hhaven/exceptions.py
hhaven/models.py
hhaven/py.typed
hhaven/utility.py
hhaven-0.2.0.dist-info/LICENSE
hhaven-0.2.0.dist-info/METADATA
hhaven-0.2.0.dist-info/WHEEL
hhaven-0.2.0.dist-info/RECORD
