Metadata-Version: 2.3
Name: hhaven
Version: 0.2.0
Summary: A well-documented and typed API wrapper for Hentai Haven.
License: MIT
Keywords: hentai-haven,hentai
Author: JokelBaf
Author-email: jokelbaf@gmail.com
Maintainer: JokelBaf
Maintainer-email: jokelbaf@gmail.com
Requires-Python: >=3.10
Classifier: Development Status :: 4 - Beta
Classifier: Intended Audience :: Developers
Classifier: Natural Language :: English
Classifier: Operating System :: OS Independent
Classifier: Programming Language :: Python
Classifier: Topic :: Internet :: WWW/HTTP
Classifier: Topic :: Software Development :: Libraries
Classifier: Topic :: Software Development :: Libraries :: Python Modules
Classifier: Topic :: Utilities
Classifier: Typing :: Typed
Requires-Dist: aiocache (>=0.12.3)
Requires-Dist: aiohttp (>=3.12.15)
Requires-Dist: pydantic (>=2.11.7)
Project-URL: Documentation, https://hhaven.nekolab.app
Project-URL: Homepage, https://github.com/jokelbaf/hhaven
Project-URL: Repository, https://github.com/jokelbaf/hhaven
